revo_module_installer/__init__.py
revo_module_installer/__main__.py
revo_module_installer/cli.py
revo_module_installer/constants.py
revo_module_installer/logging.py
revo_module_installer/config/load.py
revo_module_installer/config/manifest.py
revo_module_installer/config/registry.py
revo_module_installer/examples/__init__.py
revo_module_installer/examples/example_manifest.yml
revo_module_installer/examples/example_registry.yml
revo_module_installer/examples/module_1/example_addition.justfile
revo_module_installer/examples/module_1/example_append.justfile
revo_module_installer-0.2.0.dist-info/METADATA
revo_module_installer-0.2.0.dist-info/WHEEL
revo_module_installer-0.2.0.dist-info/entry_points.txt
revo_module_installer-0.2.0.dist-info/RECORD
