Metadata-Version: 2.4
Name: revo-module-installer
Version: 0.2.0
Summary: CLI for installing RevoData modules
Author: RevoData NL
License: MIT
Requires-Python: >=3.12
Requires-Dist: gitpython>=3.1.43
Requires-Dist: httpx>=0.27.0
Requires-Dist: pathspec>=0.12.1
Requires-Dist: platformdirs>=4.2.2
Requires-Dist: prompt-toolkit>=3.0.43
Requires-Dist: pydantic>=2.7.0
Requires-Dist: rich>=13.7.1
Requires-Dist: ruamel-yaml>=0.18.6
Requires-Dist: typer>=0.12.3
Provides-Extra: dev
Requires-Dist: flake8>=7.1.0; extra == 'dev'
Requires-Dist: pre-commit-hooks>=6.0.0; extra == 'dev'
Requires-Dist: prek==0.3.0; extra == 'dev'
Requires-Dist: pydoclint>=0.8.3; extra == 'dev'
Requires-Dist: pylint>=3.2.6; extra == 'dev'
Requires-Dist: pymarkdownlnt>=0.9.35; extra == 'dev'
Requires-Dist: pyright>=1.1.374; extra == 'dev'
Requires-Dist: pytest-cov>=5.0.0; extra == 'dev'
Requires-Dist: pytest>=8.2.0; extra == 'dev'
Requires-Dist: ruff>=0.5.5; extra == 'dev'
